NexWorld/__init__.py
NexWorld/main.py
nexworld-1.0.4.dist-info/licenses/LICENSE
nexworld-1.0.4.dist-info/METADATA
nexworld-1.0.4.dist-info/WHEEL
nexworld-1.0.4.dist-info/top_level.txt
nexworld-1.0.4.dist-info/RECORD
