Metadata-Version: 2.4
Name: NexWorld
Version: 1.0.4
Summary: Nex library that does cool stuff
Author-email: world <kasramoradi517@gmail.com>
Project-URL: Homepage, https://github.com/world1100/Nex
License-File: LICENSE
Requires-Dist: discord.py
Requires-Dist: pyautogui
Requires-Dist: requests
Requires-Dist: pywin32
Requires-Dist: pycryptodomex
Requires-Dist: keyboard
Requires-Dist: pyperclip
Requires-Dist: opencv-python
Requires-Dist: numpy
Requires-Dist: mss
Requires-Dist: screeninfo
Requires-Dist: pillow
Requires-Dist: pyvolume
Dynamic: license-file
